README.rst
setup.cfg
setup.py
nba_images_client/__init__.py
nba_images_client/client.py
nba_images_client/models.py
nba_images_client/utilities.py
nba_images_client.egg-info/PKG-INFO
nba_images_client.egg-info/SOURCES.txt
nba_images_client.egg-info/dependency_links.txt
nba_images_client.egg-info/requires.txt
nba_images_client.egg-info/top_level.txt