Metadata-Version: 1.1
Name: nba-images-client
Version: 0.0.1
Summary: NBA Images Client
Home-page: https://github.com/jaebradley/nba_images_client
Author: Jae Bradley
Author-email: jae.b.bradley@gmail.com
License: UNKNOWN
Download-URL: https://github.com/jaebradley/nba_images_client/tarball/0.1
Keywords: NBA
Platform: UNKNOWN
